my_app/__init__.py
my_app/example.py
sdfgsdfgsdfgsdfgsdfgsehdfghjdfg-0.0.1.dist-info/METADATA
sdfgsdfgsdfgsdfgsdfgsehdfghjdfg-0.0.1.dist-info/WHEEL
sdfgsdfgsdfgsdfgsdfgsehdfghjdfg-0.0.1.dist-info/top_level.txt
sdfgsdfgsdfgsdfgsdfgsehdfghjdfg-0.0.1.dist-info/RECORD
