Metadata-Version: 2.2
Name: sdfgsdfgsdfgsdfgsdfgsehdfghjdfg
Version: 0.0.1
Summary: Пример публикации на PyPI (без pyproject.toml)
Author: Ваше Имя
Author-email: youremail@example.com
Classifier: Programming Language :: Python :: 3
Classifier: License :: OSI Approved :: MIT License
Classifier: Operating System :: OS Independent
Requires-Python: >=3.7
Dynamic: author
Dynamic: author-email
Dynamic: classifier
Dynamic: description-content-type
Dynamic: requires-python
Dynamic: summary
